{"nodes": [{"id": "d_hackathon_flutter_app_simulation_screen_dart", "label": "simulation_screen.dart", "file_type": "code", "source_file": "D:\\hackathon\\Flutter_app\\simulation_screen.dart", "source_location": null}, {"id": "d_hackathon_flutter_app_simulation_screen_dart_simulationscreen", "label": "SimulationScreen", "file_type": "code", "source_file": "D:\\hackathon\\Flutter_app\\simulation_screen.dart", "source_location": null}, {"id": "d_hackathon_flutter_app_simulation_screen_dart_simulationscreenstate", "label": "_SimulationScreenState", "file_type": "code", "source_file": "D:\\hackathon\\Flutter_app\\simulation_screen.dart", "source_location": null}, {"id": "d_hackathon_flutter_app_simulation_screen_dart_statecard", "label": "_StateCard", "file_type": "code", "source_file": "D:\\hackathon\\Flutter_app\\simulation_screen.dart", "source_location": null}, {"id": "d_hackathon_flutter_app_simulation_screen_dart_metricchip", "label": "_MetricChip", "file_type": "code", "source_file": "D:\\hackathon\\Flutter_app\\simulation_screen.dart", "source_location": null}, {"id": "d_hackathon_flutter_app_simulation_screen_dart_build", "label": "build", "file_type": "code", "source_file": "D:\\hackathon\\Flutter_app\\simulation_screen.dart", "source_location": null}, {"id": "d_hackathon_flutter_app_simulation_screen_dart_scaffold", "label": "Scaffold", "file_type": "code", "source_file": "D:\\hackathon\\Flutter_app\\simulation_screen.dart", "source_location": null}, {"id": "d_hackathon_flutter_app_simulation_screen_dart_sizedbox", "label": "SizedBox", "file_type": "code", "source_file": "D:\\hackathon\\Flutter_app\\simulation_screen.dart", "source_location": null}, {"id": "d_hackathon_flutter_app_simulation_screen_dart_text", "label": "Text", "file_type": "code", "source_file": "D:\\hackathon\\Flutter_app\\simulation_screen.dart", "source_location": null}, {"id": "d_hackathon_flutter_app_simulation_screen_dart_row", "label": "Row", "file_type": "code", "source_file": "D:\\hackathon\\Flutter_app\\simulation_screen.dart", "source_location": null}, {"id": "d_hackathon_flutter_app_simulation_screen_dart_icon", "label": "Icon", "file_type": "code", "source_file": "D:\\hackathon\\Flutter_app\\simulation_screen.dart", "source_location": null}, {"id": "d_hackathon_flutter_app_simulation_screen_dart_animatedcontainer", "label": "AnimatedContainer", "file_type": "code", "source_file": "D:\\hackathon\\Flutter_app\\simulation_screen.dart", "source_location": null}, {"id": "d_hackathon_flutter_app_simulation_screen_dart_container", "label": "Container", "file_type": "code", "source_file": "D:\\hackathon\\Flutter_app\\simulation_screen.dart", "source_location": null}, {"id": "package_flutter_material_dart", "label": "package:flutter/material.dart", "file_type": "code", "source_file": "D:\\hackathon\\Flutter_app\\simulation_screen.dart", "source_location": null}, {"id": "package_flutter_animate_flutter_animate_dart", "label": "package:flutter_animate/flutter_animate.dart", "file_type": "code", "source_file": "D:\\hackathon\\Flutter_app\\simulation_screen.dart", "source_location": null}, {"id": "package_google_fonts_google_fonts_dart", "label": "package:google_fonts/google_fonts.dart", "file_type": "code", "source_file": "D:\\hackathon\\Flutter_app\\simulation_screen.dart", "source_location": null}, {"id": "models_insight_result_dart", "label": "../models/insight_result.dart", "file_type": "code", "source_file": "D:\\hackathon\\Flutter_app\\simulation_screen.dart", "source_location": null}], "edges": [{"source": "d_hackathon_flutter_app_simulation_screen_dart", "target": "d_hackathon_flutter_app_simulation_screen_dart_simulationscreen", "relation": "defines", "confidence": "EXTRACTED", "confidence_score": 1.0, "source_file": "D:\\hackathon\\Flutter_app\\simulation_screen.dart", "source_location": null, "weight": 1.0}, {"source": "d_hackathon_flutter_app_simulation_screen_dart", "target": "d_hackathon_flutter_app_simulation_screen_dart_simulationscreenstate", "relation": "defines", "confidence": "EXTRACTED", "confidence_score": 1.0, "source_file": "D:\\hackathon\\Flutter_app\\simulation_screen.dart", "source_location": null, "weight": 1.0}, {"source": "d_hackathon_flutter_app_simulation_screen_dart", "target": "d_hackathon_flutter_app_simulation_screen_dart_statecard", "relation": "defines", "confidence": "EXTRACTED", "confidence_score": 1.0, "source_file": "D:\\hackathon\\Flutter_app\\simulation_screen.dart", "source_location": null, "weight": 1.0}, {"source": "d_hackathon_flutter_app_simulation_screen_dart", "target": "d_hackathon_flutter_app_simulation_screen_dart_metricchip", "relation": "defines", "confidence": "EXTRACTED", "confidence_score": 1.0, "source_file": "D:\\hackathon\\Flutter_app\\simulation_screen.dart", "source_location": null, "weight": 1.0}, {"source": "d_hackathon_flutter_app_simulation_screen_dart", "target": "d_hackathon_flutter_app_simulation_screen_dart_build", "relation": "defines", "confidence": "EXTRACTED", "confidence_score": 1.0, "source_file": "D:\\hackathon\\Flutter_app\\simulation_screen.dart", "source_location": null, "weight": 1.0}, {"source": "d_hackathon_flutter_app_simulation_screen_dart", "target": "d_hackathon_flutter_app_simulation_screen_dart_scaffold", "relation": "defines", "confidence": "EXTRACTED", "confidence_score": 1.0, "source_file": "D:\\hackathon\\Flutter_app\\simulation_screen.dart", "source_location": null, "weight": 1.0}, {"source": "d_hackathon_flutter_app_simulation_screen_dart", "target": "d_hackathon_flutter_app_simulation_screen_dart_sizedbox", "relation": "defines", "confidence": "EXTRACTED", "confidence_score": 1.0, "source_file": "D:\\hackathon\\Flutter_app\\simulation_screen.dart", "source_location": null, "weight": 1.0}, {"source": "d_hackathon_flutter_app_simulation_screen_dart", "target": "d_hackathon_flutter_app_simulation_screen_dart_text", "relation": "defines", "confidence": "EXTRACTED", "confidence_score": 1.0, "source_file": "D:\\hackathon\\Flutter_app\\simulation_screen.dart", "source_location": null, "weight": 1.0}, {"source": "d_hackathon_flutter_app_simulation_screen_dart", "target": "d_hackathon_flutter_app_simulation_screen_dart_row", "relation": "defines", "confidence": "EXTRACTED", "confidence_score": 1.0, "source_file": "D:\\hackathon\\Flutter_app\\simulation_screen.dart", "source_location": null, "weight": 1.0}, {"source": "d_hackathon_flutter_app_simulation_screen_dart", "target": "d_hackathon_flutter_app_simulation_screen_dart_icon", "relation": "defines", "confidence": "EXTRACTED", "confidence_score": 1.0, "source_file": "D:\\hackathon\\Flutter_app\\simulation_screen.dart", "source_location": null, "weight": 1.0}, {"source": "d_hackathon_flutter_app_simulation_screen_dart", "target": "d_hackathon_flutter_app_simulation_screen_dart_animatedcontainer", "relation": "defines", "confidence": "EXTRACTED", "confidence_score": 1.0, "source_file": "D:\\hackathon\\Flutter_app\\simulation_screen.dart", "source_location": null, "weight": 1.0}, {"source": "d_hackathon_flutter_app_simulation_screen_dart", "target": "d_hackathon_flutter_app_simulation_screen_dart_container", "relation": "defines", "confidence": "EXTRACTED", "confidence_score": 1.0, "source_file": "D:\\hackathon\\Flutter_app\\simulation_screen.dart", "source_location": null, "weight": 1.0}, {"source": "d_hackathon_flutter_app_simulation_screen_dart", "target": "package_flutter_material_dart", "relation": "imports", "confidence": "EXTRACTED", "confidence_score": 1.0, "source_file": "D:\\hackathon\\Flutter_app\\simulation_screen.dart", "source_location": null, "weight": 1.0}, {"source": "d_hackathon_flutter_app_simulation_screen_dart", "target": "package_flutter_animate_flutter_animate_dart", "relation": "imports", "confidence": "EXTRACTED", "confidence_score": 1.0, "source_file": "D:\\hackathon\\Flutter_app\\simulation_screen.dart", "source_location": null, "weight": 1.0}, {"source": "d_hackathon_flutter_app_simulation_screen_dart", "target": "package_google_fonts_google_fonts_dart", "relation": "imports", "confidence": "EXTRACTED", "confidence_score": 1.0, "source_file": "D:\\hackathon\\Flutter_app\\simulation_screen.dart", "source_location": null, "weight": 1.0}, {"source": "d_hackathon_flutter_app_simulation_screen_dart", "target": "models_insight_result_dart", "relation": "imports", "confidence": "EXTRACTED", "confidence_score": 1.0, "source_file": "D:\\hackathon\\Flutter_app\\simulation_screen.dart", "source_location": null, "weight": 1.0}]}